gspread_datarame/__init__.py
gspread_datarame-0.1.0.dist-info/LICENSE
gspread_datarame-0.1.0.dist-info/METADATA
gspread_datarame-0.1.0.dist-info/WHEEL
gspread_datarame-0.1.0.dist-info/top_level.txt
gspread_datarame-0.1.0.dist-info/RECORD
